[
  {"name": "周杰倫", "name_english": "Jay Chou", "category": "Singer"},
  {"name": "鄧紫棋", "name_english": "G.E.M.", "category": "Singer"},
  {"name": "五月天", "name_english": "Mayday", "category": "Singer"},
  {"name": "天后王菲", "name_english": "Faye Wong", "category": "Singer"},
  {"name": "李克勤", "name_english": "Hacken Lee", "category": "Singer"},
  {"name": "陶喆", "name_english": "David Tao", "category": "Singer"},
  {"name": "楊丞琳", "name_english": "Rainie Yang", "category": "Singer"},
  {"name": "丁當", "name_english": "Ding Dang", "category": "Singer"},
  {"name": "蔡依林", "name_english": "Jolin Tsai", "category": "Singer"},
  {"name": "陳奕迅", "name_english": "Eason Chan", "category": "Singer"},
  {"name": "林依晨", "name_english": "Ariel Lin", "category": "Actress"},
  {"name": "隋棠", "name_english": "Vicky Sui", "category": "Actress"},
  {"name": "夏于喬", "name_english": "Hsia Yu-chiao", "category": "Actress"},
  {"name": "李智恩", "name_english": "Lee Ji-eun", "category": "Actress"},
  {"name": "林俊傑", "name_english": "JJ Lin", "category": "Singer"},
  {"name": "黃渤", "name_english": "Huang Bo", "category": "Actor"},
  {"name": "古天樂", "name_english": "Louis Koo", "category": "Actor"},
  {"name": "王力宏", "name_english": "Leehom Wang", "category": "Singer"},
  {"name": "張宇", "name_english": "Michael Tsung", "category": "Singer"},
  {"name": "李宗盛", "name_english": "Lee Tzong-Sheng", "category": "Singer"},
  {"name": "童安格", "name_english": "Tung An-le", "category": "Singer"},
  {"name": "許茹芸", "name_english": "Shauni Hsu", "category": "Singer"},
  {"name": "范曉萱", "name_english": "Charlene Choi", "category": "Singer"},
  {"name": "容祖兒", "name_english": "Joey Yung", "category": "Singer"},
  {"name": "巫迪文", "name_english": "Dee Hsu", "category": "Host"},
  {"name": "吳宗憲", "name_english": "Jacky Wu", "category": "Host"},
  {"name": "胡瓜", "name_english": "Hu Gua", "category": "Host"},
  {"name": "曾寶儀", "name_english": "Bao Yi Zeng", "category": "Host"},
  {"name": "陶晶瑩", "name_english": "Cecilia Tao", "category": "Host"},
  {"name": "小S", "name_english": "Hsiao Shu", "category": "Host"},
  {"name": "阿雅", "name_english": "A-ya", "category": "Host"},
  {"name": "張韶涵", "name_english": "Angela Zhang", "category": "Singer"},
  {"name": "徐若瑄", "name_english": "Vivian Hsu", "category": "Actress"},
  {"name": "林熙蕾", "name_english": "Chen Hao-sen", "category": "Actress"},
  {"name": "言承旭", "name_english": "Jerry Yan", "category": "Actor"},
  {"name": "溫兆倫", "name_english": "van Wen", "category": "Actor"},
  {"name": "黃曉明", "name_english": "Huang Xiaoming", "category": "Actor"},
  {"name": "范冰冰", "name_english": "Fan Bingbing", "category": "Actress"},
  {"name": "台灣Selena", "name_english": "Selena Gomez TW", "category": "Singer"},
  {"name": "林志玲", "name_english": "Lin Chi-ling", "category": "Model"},
  {"name": "小彩旗", "name_english": "Xiao Cai Qi", "category": "Dancer"},
  {"name": "張惠妹", "name_english": "A-Mei", "category": "Singer"},
  {"name": "王菀之", "name_english": "Ivana Wong", "category": "Singer"},
  {"name": "林嘉欣", "name_english": "Karena Lam", "category": "Actress"},
  {"name": "鍾欣潼", "name_english": "Gillian Chung", "category": "Singer"},
  {"name": "阿嬌鍾欣怡", "name_english": "Charlene Choi", "category": "Singer"},
  {"name": "蔡健雅", "name_english": "Tanya Chua", "category": "Singer"},
  {"name": "張柏芝", "name_english": "Cecilia Cheung", "category": "Actress"},
  {"name": "舒淇", "name_english": "Shu Qi", "category": "Actress"},
  {"name": "李冰冰", "name_english": "Li Bingbing", "category": "Actress"},
  {"name": "趙薇", "name_english": "Vicki Zhao", "category": "Actress"},
  {"name": "楊冪", "name_english": "Yang Mi", "category": "Actress"},
  {"name": "唐嫣", "name_english": "Tia Tang", "category": "Actress"},
  {"name": "郭碧婷", "name_english": "Bea Hayden Kuo", "category": "Actress"},
  {"name": "秦嵐", "name_english": "Qin Lan", "category": "Actress"},
  {"name": "陳妍希", "name_english": "Michelle Chen", "category": "Actress"},
  {"name": "賈靜雯", "name_english": "Jia Jing-wen", "category": "Actress"},
  {"name": "海清", "name_english": "Haiqing", "category": "Actress"},
  {"name": "倪妮", "name_english": "Ni Ni", "category": "Actress"},
  {"name": "江南春", "name_english": "Jiangnan Chun", "category": "Actor"},
  {"name": "段奕宏", "name_english": "Duanyi Hong", "category": "Actor"},
  {"name": "孫紅雷", "name_english": "Sun Honglei", "category": "Actor"},
  {"name": "陳寶國", "name_english": "Chen Baoguo", "category": "Actor"},
  {"name": "常林", "name_english": "Chang Lin", "category": "Actor"},
  {"name": "郭富城", "name_english": "Aaron Kwok", "category": "Singer"},
  {"name": "黎明", "name_english": "Leon Lai", "category": "Singer"},
  {"name": "張學友", "name_english": "Jacky Cheung", "category": "Singer"},
  {"name": "吳奇隆", "name_english": "Nicky Wu", "category": "Singer"},
  {"name": "蘇有朋", "name_english": "Alec Su", "category": "Singer"},
  {"name": "朱孝天", "name_english": "Zhu Xiaochen", "category": "Singer"},
  {"name": "吳建豪", "name_english": "Will Wu", "category": "Singer"},
  {"name": "羅志祥", "name_english": "Show Lo", "category": "Singer"},
  {"name": "炎亞綸", "name_english": "Aaron Yan", "category": "Singer"},
  {"name": "飛輪海", "name_english": "Fahrenheit", "category": "Singer"},
  {"name": "南拳媽媽", "name_english": "NanoM", "category": "Singer"},
  {"name": "將進酒", "name_english": "Jing Wine", "category": "Singer"},
  {"name": "S.H.E", "name_english": "S.H.E", "category": "Singer"},
  {"name": "Twins", "name_english": "Twins", "category": "Singer"},
  {"name": "2NE1", "name_english": "2NE1", "category": "Singer"},
  {"name": "BIGBANG", "name_english": "BIGBANG", "category": "Singer"},
  {"name": "少女時代", "name_english": "Girls Generation", "category": "Singer"},
  {"name": "EXO", "name_english": "EXO", "category": "Singer"},
  {"name": "BTS", "name_english": "BTS", "category": "Singer"},
  {"name": "BLACKPINK", "name_english": "BLACKPINK", "category": "Singer"},
  {"name": "TWICE", "name_english": "TWICE", "category": "Singer"},
  {"name": "RED VELVET", "name_english": "RED VELVET", "category": "Singer"},
  {"name": "SEVENTEEN", "name_english": "SEVENTEEN", "category": "Singer"},
  {"name": "宮崎駿", "name_english": "Hayao Miyazaki", "category": "Director"},
  {"name": "是枝裕和", "name_english": "Hirokazu Koreeda", "category": "Director"},
  {"name": "黑澤明", "name_english": "Akira Kurosawa", "category": "Director"},
  {"name": "侯孝賢", "name_english": "Hou Hsiao-hsien", "category": "Director"},
  {"name": "成龍", "name_english": "Jackie Chan", "category": "Actor"},
  {"name": "李連杰", "name_english": "Jet Li", "category": "Actor"},
  {"name": "吳京", "name_english": "Wu Jing", "category": "Actor"},
  {"name": "甄子丹", "name_english": "Donnie Yen", "category": "Actor"},
  {"name": "洪金寶", "name_english": "Sammo Hung", "category": "Actor"},
  {"name": "林青霞", "name_english": "Brigitte Lin", "category": "Actress"},
  {"name": "梅豔芳", "name_english": "Anita Mui", "category": "Singer"},
  {"name": "周潤發", "name_english": "Chow Yun-fat", "category": "Actor"},
  {"name": "湯唯", "name_english": "Tang Wei", "category": "Actress"}
]
